batchframe/__init__.py
batchframe/_version.py
batchframe/cli.py
batchframe/executor.py
batchframe/helpers.py
batchframe/py.typed
batchframe/visuals.py
batchframe/models/__init__.py
batchframe/models/batchframe_param.py
batchframe/models/configuration.py
batchframe/models/service.py
batchframe/models/source.py
batchframe-0.0.1a13.dist-info/LICENSE.txt
batchframe-0.0.1a13.dist-info/METADATA
batchframe-0.0.1a13.dist-info/WHEEL
batchframe-0.0.1a13.dist-info/entry_points.txt
batchframe-0.0.1a13.dist-info/top_level.txt
batchframe-0.0.1a13.dist-info/RECORD
