Metadata-Version: 2.1
Name: batchframe
Version: 0.0.1a13
Summary: Batteries-included framework for running repeatable tasks.
Home-page: https://gitlab.com/Dzeri96/batchframe
Author: Dzeri96
Author-email: dzeri96@proton.me
License: GPL-3.0-or-later
Project-URL: Source, https://gitlab.com/Dzeri96/batchframe
Platform: any
Classifier: Development Status :: 3 - Alpha
Classifier: Programming Language :: Python
Classifier: License :: OSI Approved :: GNU Lesser General Public License v3 or later (LGPLv3+)
Requires-Python: >=3.8
License-File: LICENSE.txt
Requires-Dist: ipython
Requires-Dist: kink
Requires-Dist: nest-asyncio
Requires-Dist: aiorwlock
Requires-Dist: rich
Requires-Dist: importlib-metadata ; python_version < "3.8"
Provides-Extra: testing
Requires-Dist: setuptools ; extra == 'testing'
Requires-Dist: pytest ; extra == 'testing'
Requires-Dist: pytest-cov ; extra == 'testing'
Requires-Dist: pytest-asyncio ; extra == 'testing'
Requires-Dist: pytest-mock ; extra == 'testing'
Requires-Dist: tox ; extra == 'testing'
Requires-Dist: mypy ; extra == 'testing'
